{
  "id": "mg0oyxvogqhp98qughd",
  "name": "Weber Golden Romance",
  "description": "Warm, golden outdoor fashion tones with lifted shadows and gentle contrast for a romantic, nostalgic Bruce Weber vibe. Subtle grain and warm shadow/highlight grading emulate golden-hour elegance while keeping skin tones natural.",
  "results": [
    {
      "success": true,
      "metadata": {
        "aiAdjustments": {
          "treatment": "color",
          "camera_profile": "Adobe Portrait",
          "confidence": 0.83,
          "exposure": 0.2,
          "highlights": -20,
          "shadows": 22,
          "whites": 10,
          "blacks": 8,
          "contrast": 15,
          "clarity": -8,
          "vibrance": 12,
          "saturation": 6,
          "color_grade_shadow_hue": 20,
          "color_grade_shadow_sat": 15,
          "color_grade_shadow_lum": 6,
          "color_grade_midtone_hue": 30,
          "color_grade_midtone_sat": 6,
          "color_grade_midtone_lum": 4,
          "color_grade_highlight_hue": 15,
          "color_grade_highlight_sat": 10,
          "color_grade_highlight_lum": -4,
          "hue_red": -5,
          "hue_orange": -5,
          "hue_yellow": -10,
          "hue_green": 10,
          "hue_aqua": -10,
          "hue_blue": -5,
          "hue_purple": 0,
          "hue_magenta": -5,
          "sat_red": -5,
          "sat_orange": 8,
          "sat_yellow": -10,
          "sat_green": -20,
          "sat_aqua": -15,
          "sat_blue": -10,
          "sat_purple": -20,
          "sat_magenta": -15,
          "lum_red": 5,
          "lum_orange": 4,
          "lum_yellow": -5,
          "lum_green": -5,
          "lum_aqua": -5,
          "lum_blue": -8,
          "lum_purple": 0,
          "lum_magenta": 0,
          "grain_amount": 16,
          "grain_size": 28,
          "grain_frequency": 55,
          "vignette_amount": -10,
          "vignette_midpoint": 50,
          "vignette_feather": 65,
          "vignette_roundness": 0,
          "vignette_style": 1,
          "tone_curve": [
            {
              "input": 0,
              "output": 18
            },
            {
              "input": 32,
              "output": 28
            },
            {
              "input": 128,
              "output": 130
            },
            {
              "input": 200,
              "output": 208
            },
            {
              "input": 255,
              "output": 245
            }
          ],
          "tone_curve_red": [
            {
              "input": 0,
              "output": 0
            },
            {
              "input": 64,
              "output": 68
            },
            {
              "input": 128,
              "output": 140
            },
            {
              "input": 200,
              "output": 224
            },
            {
              "input": 255,
              "output": 255
            }
          ],
          "tone_curve_green": [
            {
              "input": 0,
              "output": 0
            },
            {
              "input": 64,
              "output": 62
            },
            {
              "input": 128,
              "output": 134
            },
            {
              "input": 200,
              "output": 210
            },
            {
              "input": 255,
              "output": 255
            }
          ],
          "tone_curve_blue": [
            {
              "input": 0,
              "output": 0
            },
            {
              "input": 64,
              "output": 54
            },
            {
              "input": 128,
              "output": 124
            },
            {
              "input": 200,
              "output": 200
            },
            {
              "input": 255,
              "output": 248
            }
          ],
          "preset_name": "Weber Golden Romance",
          "description": "Warm, golden outdoor fashion tones with lifted shadows and gentle contrast for a romantic, nostalgic Bruce Weber vibe. Subtle grain and warm shadow/highlight grading emulate golden-hour elegance while keeping skin tones natural.",
          "masks": [
            {
              "name": "Face Skin",
              "type": "face_skin",
              "adjustments": {
                "shadows": 0.12,
                "clarity": -0.06,
                "texture": -0.08
              },
              "subCategoryId": 1,
              "confidence": 0.75,
              "detectionQuality": 0.75
            },
            {
              "name": "Eye Pop",
              "type": "iris_pupil",
              "adjustments": {
                "clarity": 0.12,
                "texture": 0.12,
                "saturation": 0.08
              },
              "subCategoryId": 2,
              "confidence": 0.75,
              "detectionQuality": 0.75
            },
            {
              "name": "Background Warm Air",
              "type": "background",
              "adjustments": {
                "highlights": -0.06,
                "shadows": 0.08,
                "dehaze": -0.06,
                "saturation": 0.06
              },
              "subCategoryId": 22,
              "confidence": 0.7,
              "detectionQuality": 0.7
            }
          ]
        },
        "confidence": 0.83
      }
    }
  ]
}
